hf_benchmark/__init__.py
hf_benchmark/cli.py
hf_benchmark/device.py
hf_benchmark/metrics.py
hf_benchmark/profiler.py
hf_benchmark/runner.py
hf_benchmark/throughput.py
hf_inference_benchmark-0.1.4.dist-info/licenses/LICENSE
hf_inference_benchmark-0.1.4.dist-info/METADATA
hf_inference_benchmark-0.1.4.dist-info/WHEEL
hf_inference_benchmark-0.1.4.dist-info/entry_points.txt
hf_inference_benchmark-0.1.4.dist-info/top_level.txt
hf_inference_benchmark-0.1.4.dist-info/RECORD
