Metadata-Version: 2.4
Name: hf-inference-benchmark
Version: 0.1.4
Summary: Production-grade HuggingFace inference benchmarking tool
Author: Yuvraj
Requires-Python: >=3.8
License-File: LICENSE
Requires-Dist: torch
Requires-Dist: transformers>=4.38
Requires-Dist: tqdm>=4.0.0
Requires-Dist: click>=8.0.0
Requires-Dist: psutil
Dynamic: license-file
